Sum_Rest.v
module sumador_1bt (
    input A,
    input B,
    input cin,
    output s,
    output cout
);
    assign s = A ^ B ^ cin;
    assign cout = (A & B) | (cin & (A ^ B));
endmodule


module sumador_4bt (
    input [3:0] A,
    input [3:0] B,
    input Sel,
    output [3:0] So,
    output Co
);
    wire [3:0] B_xor_Sel;
    wire c0, c1, c2;

   
    assign B_xor_Sel = B ^ {4{Sel}};


    sumador_1bt fa0 (A[0], B_xor_Sel[0], Sel, So[0], c0);
    sumador_1bt fa1 (A[1], B_xor_Sel[1], c0,  So[1], c1);
    sumador_1bt fa2 (A[2], B_xor_Sel[2], c1,  So[2], c2);
    sumador_1bt fa3 (A[3], B_xor_Sel[3], c2,  So[3], Co);

endmodule

module tb;
    reg [3:0] A, B;
    reg Sel;
    wire [3:0] So;
    wire Co;
   
   
    reg [4:0] i, j, k;

    sumador_4bt uut (A, B, Sel, So, Co);

    initial begin
        $dumpfile("resultado.vcd");
        $dumpvars(0, tb);

        for (k = 0; k < 2; k = k + 1) begin
            Sel = k[0];
            for (i = 0; i < 16; i = i + 1) begin
                A = i[3:0];
                for (j = 0; j < 16; j = j + 1) begin
                    B = j[3:0];
                    #5;
                end
            end
        end
        $finish;
    end
endmodule

build/resultado.vcd
$date
	Wed Mar 11 18:42:11 2026
$end
$version
	Icarus Verilog
$end
$timescale
	1s
$end
$scope module tb $end
$var wire 4 ! So [3:0] $end
$var wire 1 " Co $end
$var reg 4 # A [3:0] $end
$var reg 4 $ B [3:0] $end
$var reg 1 % Sel $end
$var reg 5 & i [4:0] $end
$var reg 5 ' j [4:0] $end
$var reg 5 ( k [4:0] $end
$scope module uut $end
$var wire 4 ) A [3:0] $end
$var wire 4 * B [3:0] $end
$var wire 4 + B_xor_Sel [3:0] $end
$var wire 1 % Sel $end
$var wire 1 , c2 $end
$var wire 1 - c1 $end
$var wire 1 . c0 $end
$var wire 4 / So [3:0] $end
$var wire 1 " Co $end
$scope module fa0 $end
$var wire 1 0 A $end
$var wire 1 1 B $end
$var wire 1 % cin $end
$var wire 1 . cout $end
$var wire 1 2 s $end
$upscope $end
$scope module fa1 $end
$var wire 1 3 A $end
$var wire 1 4 B $end
$var wire 1 . cin $end
$var wire 1 - cout $end
$var wire 1 5 s $end
$upscope $end
$scope module fa2 $end
$var wire 1 6 A $end
$var wire 1 7 B $end
$var wire 1 - cin $end
$var wire 1 , cout $end
$var wire 1 8 s $end
$upscope $end
$scope module fa3 $end
$var wire 1 9 A $end
$var wire 1 : B $end
$var wire 1 , cin $end
$var wire 1 " cout $end
$var wire 1 ; s $end
$upscope $end
$upscope $end
$upscope $end
$enddefinitions $end
$comment Show the parameter values. $end
$dumpall
$end
#0
$dumpvars
0;
0:
09
08
07
06
05
04
03
02
01
00
b0 /
0.
0-
0,
b0 +
b0 *
b0 )
b0 (
b0 '
b0 &
0%
b0 $
b0 #
0"
b0 !
$end
#5
b1 !
b1 /
12
11
b1 +
b1 $
b1 *
b1 '
#10
02
b10 !
b10 /
15
01
14
b10 +
b10 $
b10 *
b10 '
#15
b11 !
b11 /
12
11
b11 +
b11 $
b11 *
b11 '
#20
02
05
b100 !
b100 /
18
01
04
17
b100 +
b100 $
b100 *
b100 '
#25
b101 !
b101 /
12
11
b101 +
b101 $
b101 *
b101 '
#30
02
b110 !
b110 /
15
01
14
b110 +
b110 $
b110 *
b110 '
#35
b111 !
b111 /
12
11
b111 +
b111 $
b111 *
b111 '
#40
02
05
08
b1000 !
b1000 /
1;
01
04
07
1:
b1000 +
b1000 $
b1000 *
b1000 '
#45
b1001 !
b1001 /
12
11
b1001 +
b1001 $
b1001 *
b1001 '
#50
02
b1010 !
b1010 /
15
01
14
b1010 +
b1010 $
b1010 *
b1010 '
#55
b1011 !
b1011 /
12
11
b1011 +
b1011 $
b1011 *
b1011 '
#60
02
05
b1100 !
b1100 /
18
01
04
17
b1100 +
b1100 $
b1100 *
b1100 '
#65
b1101 !
b1101 /
12
11
b1101 +
b1101 $
b1101 *
b1101 '
#70
02
b1110 !
b1110 /
15
01
14
b1110 +
b1110 $
b1110 *
b1110 '
#75
b1111 !
b1111 /
12
11
b1111 +
b1111 $
b1111 *
b1111 '
#80
05
08
0;
b1 !
b1 /
12
0.
01
04
07
0:
b0 +
10
b0 $
b0 *
b1 #
b1 )
b1 &
b0 '
#85
15
b10 !
b10 /
02
1.
11
b1 +
b1 $
b1 *
b1 '
#90
08
0-
12
0.
b11 !
b11 /
15
01
14
b10 +
b10 $
b10 *
b10 '
#95
18
1-
05
b100 !
b100 /
02
1.
11
b11 +
b11 $
b11 *
b11 '
#100
0;
0-
0,
12
0.
05
b101 !
b101 /
18
01
04
17
b100 +
b100 $
b100 *
b100 '
#105
15
b110 !
b110 /
02
1.
11
b101 +
b101 $
b101 *
b101 '
#110
0;
0,
18
0-
12
0.
b111 !
b111 /
15
01
14
b110 +
b110 $
b110 *
b110 '
#115
1;
1,
08
1-
05
b1000 !
b1000 /
02
1.
11
b111 +
b111 $
b111 *
b111 '
#120
0-
0,
0"
12
0.
05
08
b1001 !
b1001 /
1;
01
04
07
1:
b1000 +
b1000 $
b1000 *
b1000 '
#125
15
b1010 !
b1010 /
02
1.
11
b1001 +
b1001 $
b1001 *
b1001 '
#130
08
0-
12
0.
b1011 !
b1011 /
15
01
14
b1010 +
b1010 $
b1010 *
b1010 '
#135
18
1-
05
b1100 !
b1100 /
02
1.
11
b1011 +
b1011 $
b1011 *
b1011 '
#140
0"
1;
0-
0,
12
0.
05
b1101 !
b1101 /
18
01
04
17
b1100 +
b1100 $
b1100 *
b1100 '
#145
15
b1110 !
b1110 /
02
1.
11
b1101 +
b1101 $
b1101 *
b1101 '
#150
0"
1;
0,
18
0-
12
0.
b1111 !
b1111 /
15
01
14
b1110 +
b1110 $
b1110 *
b1110 '
#155
1"
0;
1,
08
1-
05
b0 !
b0 /
02
1.
11
b1111 +
b1111 $
b1111 *
b1111 '
#160
0,
0"
0-
08
0;
02
0.
b10 !
b10 /
15
01
04
07
0:
b0 +
00
13
b0 $
b0 *
b10 #
b10 )
b10 &
b0 '
#165
b11 !
b11 /
12
11
b1 +
b1 $
b1 *
b1 '
#170
18
02
b100 !
b100 /
05
1-
01
14
b10 +
b10 $
b10 *
b10 '
#175
b101 !
b101 /
12
11
b11 +
b11 $
b11 *
b11 '
#180
0;
0,
02
15
0-
b110 !
b110 /
18
01
04
17
b100 +
b100 $
b100 *
b100 '
#185
b111 !
b111 /
12
11
b101 +
b101 $
b101 *
b101 '
#190
1;
1,
08
02
b1000 !
b1000 /
05
1-
01
14
b110 +
b110 $
b110 *
b110 '
#195
b1001 !
b1001 /
12
11
b111 +
b111 $
b111 *
b111 '
#200
0,
0"
02
15
0-
08
b1010 !
b1010 /
1;
01
04
07
1:
b1000 +
b1000 $
b1000 *
b1000 '
#205
b1011 !
b1011 /
12
11
b1001 +
b1001 $
b1001 *
b1001 '
#210
18
02
b1100 !
b1100 /
05
1-
01
14
b1010 +
b1010 $
b1010 *
b1010 '
#215
b1101 !
b1101 /
12
11
b1011 +
b1011 $
b1011 *
b1011 '
#220
0"
1;
0,
02
15
0-
b1110 !
b1110 /
18
01
04
17
b1100 +
b1100 $
b1100 *
b1100 '
#225
b1111 !
b1111 /
12
11
b1101 +
b1101 $
b1101 *
b1101 '
#230
1"
0;
1,
08
02
b0 !
b0 /
05
1-
01
14
b1110 +
b1110 $
b1110 *
b1110 '
#235
b1 !
b1 /
12
11
b1111 +
b1111 $
b1111 *
b1111 '
#240
0-
15
0,
0"
08
0;
b11 !
b11 /
12
0.
01
04
07
0:
b0 +
10
b0 $
b0 *
b11 #
b11 )
b11 &
b0 '
#245
18
1-
05
b100 !
b100 /
02
1.
11
b1 +
b1 $
b1 *
b1 '
#250
12
0.
b101 !
b101 /
05
01
14
b10 +
b10 $
b10 *
b10 '
#255
15
b110 !
b110 /
02
1.
11
b11 +
b11 $
b11 *
b11 '
#260
0-
0;
0,
12
0.
15
b111 !
b111 /
18
01
04
17
b100 +
b100 $
b100 *
b100 '
#265
1;
1,
08
1-
05
b1000 !
b1000 /
02
1.
11
b101 +
b101 $
b101 *
b101 '
#270
12
0.
b1001 !
b1001 /
05
01
14
b110 +
b110 $
b110 *
b110 '
#275
15
b1010 !
b1010 /
02
1.
11
b111 +
b111 $
b111 *
b111 '
#280
0-
0,
0"
12
0.
15
08
b1011 !
b1011 /
1;
01
04
07
1:
b1000 +
b1000 $
b1000 *
b1000 '
#285
18
1-
05
b1100 !
b1100 /
02
1.
11
b1001 +
b1001 $
b1001 *
b1001 '
#290
12
0.
b1101 !
b1101 /
05
01
14
b1010 +
b1010 $
b1010 *
b1010 '
#295
15
b1110 !
b1110 /
02
1.
11
b1011 +
b1011 $
b1011 *
b1011 '
#300
0"
0-
1;
0,
12
0.
15
b1111 !
b1111 /
18
01
04
17
b1100 +
b1100 $
b1100 *
b1100 '
#305
1"
0;
1,
08
1-
05
b0 !
b0 /
02
1.
11
b1101 +
b1101 $
b1101 *
b1101 '
#310
12
0.
b1 !
b1 /
05
01
14
b1110 +
b1110 $
b1110 *
b1110 '
#315
15
b10 !
b10 /
02
1.
11
b1111 +
b1111 $
b1111 *
b1111 '
#320
0,
0"
0-
0;
02
0.
05
b100 !
b100 /
18
01
04
07
0:
b0 +
00
03
16
b0 $
b0 *
b100 #
b100 )
b100 &
b0 '
#325
b101 !
b101 /
12
11
b1 +
b1 $
b1 *
b1 '
#330
02
b110 !
b110 /
15
01
14
b10 +
b10 $
b10 *
b10 '
#335
b111 !
b111 /
12
11
b11 +
b11 $
b11 *
b11 '
#340
1;
02
05
b1000 !
b1000 /
08
1,
01
04
17
b100 +
b100 $
b100 *
b100 '
#345
b1001 !
b1001 /
12
11
b101 +
b101 $
b101 *
b101 '
#350
02
b1010 !
b1010 /
15
01
14
b110 +
b110 $
b110 *
b110 '
#355
b1011 !
b1011 /
12
11
b111 +
b111 $
b111 *
b111 '
#360
0"
02
05
18
0,
b1100 !
b1100 /
1;
01
04
07
1:
b1000 +
b1000 $
b1000 *
b1000 '
#365
b1101 !
b1101 /
12
11
b1001 +
b1001 $
b1001 *
b1001 '
#370
02
b1110 !
b1110 /
15
01
14
b1010 +
b1010 $
b1010 *
b1010 '
#375
b1111 !
b1111 /
12
11
b1011 +
b1011 $
b1011 *
b1011 '
#380
1"
0;
02
05
b0 !
b0 /
08
1,
01
04
17
b1100 +
b1100 $
b1100 *
b1100 '
#385
b1 !
b1 /
12
11
b1101 +
b1101 $
b1101 *
b1101 '
#390
02
b10 !
b10 /
15
01
14
b1110 +
b1110 $
b1110 *
b1110 '
#395
b11 !
b11 /
12
11
b1111 +
b1111 $
b1111 *
b1111 '
#400
05
0"
18
0,
0;
b101 !
b101 /
12
0.
01
04
07
0:
b0 +
10
b0 $
b0 *
b101 #
b101 )
b101 &
b0 '
#405
15
b110 !
b110 /
02
1.
11
b1 +
b1 $
b1 *
b1 '
#410
0;
0,
18
0-
12
0.
b111 !
b111 /
15
01
14
b10 +
b10 $
b10 *
b10 '
#415
1;
1,
08
1-
05
b1000 !
b1000 /
02
1.
11
b11 +
b11 $
b11 *
b11 '
#420
0-
12
0.
05
b1001 !
b1001 /
08
01
04
17
b100 +
b100 $
b100 *
b100 '
#425
15
b1010 !
b1010 /
02
1.
11
b101 +
b101 $
b101 *
b101 '
#430
08
0-
12
0.
b1011 !
b1011 /
15
01
14
b110 +
b110 $
b110 *
b110 '
#435
18
1-
05
b1100 !
b1100 /
02
1.
11
b111 +
b111 $
b111 *
b111 '
#440
0,
0-
0"
12
0.
05
18
b1101 !
b1101 /
1;
01
04
07
1:
b1000 +
b1000 $
b1000 *
b1000 '
#445
15
b1110 !
b1110 /
02
1.
11
b1001 +
b1001 $
b1001 *
b1001 '
#450
0"
1;
0,
18
0-
12
0.
b1111 !
b1111 /
15
01
14
b1010 +
b1010 $
b1010 *
b1010 '
#455
1"
0;
1,
08
1-
05
b0 !
b0 /
02
1.
11
b1011 +
b1011 $
b1011 *
b1011 '
#460
0-
12
0.
05
b1 !
b1 /
08
01
04
17
b1100 +
b1100 $
b1100 *
b1100 '
#465
15
b10 !
b10 /
02
1.
11
b1101 +
b1101 $
b1101 *
b1101 '
#470
08
0-
12
0.
b11 !
b11 /
15
01
14
b1110 +
b1110 $
b1110 *
b1110 '
#475
18
1-
05
b100 !
b100 /
02
1.
11
b1111 +
b1111 $
b1111 *
b1111 '
#480
0,
0"
0-
18
0;
02
0.
b110 !
b110 /
15
01
04
07
0:
b0 +
00
13
b0 $
b0 *
b110 #
b110 )
b110 &
b0 '
#485
b111 !
b111 /
12
11
b1 +
b1 $
b1 *
b1 '
#490
1;
1,
08
02
b1000 !
b1000 /
05
1-
01
14
b10 +
b10 $
b10 *
b10 '
#495
b1001 !
b1001 /
12
11
b11 +
b11 $
b11 *
b11 '
#500
02
15
0-
b1010 !
b1010 /
08
01
04
17
b100 +
b100 $
b100 *
b100 '
#505
b1011 !
b1011 /
12
11
b101 +
b101 $
b101 *
b101 '
#510
18
02
b1100 !
b1100 /
05
1-
01
14
b110 +
b110 $
b110 *
b110 '
#515
b1101 !
b1101 /
12
11
b111 +
b111 $
b111 *
b111 '
#520
0,
0"
02
15
0-
18
b1110 !
b1110 /
1;
01
04
07
1:
b1000 +
b1000 $
b1000 *
b1000 '
#525
b1111 !
b1111 /
12
11
b1001 +
b1001 $
b1001 *
b1001 '
#530
1"
0;
1,
08
02
b0 !
b0 /
05
1-
01
14
b1010 +
b1010 $
b1010 *
b1010 '
#535
b1 !
b1 /
12
11
b1011 +
b1011 $
b1011 *
b1011 '
#540
02
15
0-
b10 !
b10 /
08
01
04
17
b1100 +
b1100 $
b1100 *
b1100 '
#545
b11 !
b11 /
12
11
b1101 +
b1101 $
b1101 *
b1101 '
#550
18
02
b100 !
b100 /
05
1-
01
14
b1110 +
b1110 $
b1110 *
b1110 '
#555
b101 !
b101 /
12
11
b1111 +
b1111 $
b1111 *
b1111 '
#560
0,
0-
15
0"
18
0;
b111 !
b111 /
12
0.
01
04
07
0:
b0 +
10
b0 $
b0 *
b111 #
b111 )
b111 &
b0 '
#565
1;
1,
08
1-
05
b1000 !
b1000 /
02
1.
11
b1 +
b1 $
b1 *
b1 '
#570
12
0.
b1001 !
b1001 /
05
01
14
b10 +
b10 $
b10 *
b10 '
#575
15
b1010 !
b1010 /
02
1.
11
b11 +
b11 $
b11 *
b11 '
#580
0-
12
0.
15
b1011 !
b1011 /
08
01
04
17
b100 +
b100 $
b100 *
b100 '
#585
18
1-
05
b1100 !
b1100 /
02
1.
11
b101 +
b101 $
b101 *
b101 '
#590
12
0.
b1101 !
b1101 /
05
01
14
b110 +
b110 $
b110 *
b110 '
#595
15
b1110 !
b1110 /
02
1.
11
b111 +
b111 $
b111 *
b111 '
#600
0,
0-
0"
12
0.
15
18
b1111 !
b1111 /
1;
01
04
07
1:
b1000 +
b1000 $
b1000 *
b1000 '
#605
1"
0;
1,
08
1-
05
b0 !
b0 /
02
1.
11
b1001 +
b1001 $
b1001 *
b1001 '
#610
12
0.
b1 !
b1 /
05
01
14
b1010 +
b1010 $
b1010 *
b1010 '
#615
15
b10 !
b10 /
02
1.
11
b1011 +
b1011 $
b1011 *
b1011 '
#620
0-
12
0.
15
b11 !
b11 /
08
01
04
17
b1100 +
b1100 $
b1100 *
b1100 '
#625
18
1-
05
b100 !
b100 /
02
1.
11
b1101 +
b1101 $
b1101 *
b1101 '
#630
12
0.
b101 !
b101 /
05
01
14
b1110 +
b1110 $
b1110 *
b1110 '
#635
15
b110 !
b110 /
02
1.
11
b1111 +
b1111 $
b1111 *
b1111 '
#640
0"
0,
0-
02
0.
05
08
b1000 !
b1000 /
1;
01
04
07
0:
b0 +
00
03
06
19
b0 $
b0 *
b1000 #
b1000 )
b1000 &
b0 '
#645
b1001 !
b1001 /
12
11
b1 +
b1 $
b1 *
b1 '
#650
02
b1010 !
b1010 /
15
01
14
b10 +
b10 $
b10 *
b10 '
#655
b1011 !
b1011 /
12
11
b11 +
b11 $
b11 *
b11 '
#660
02
05
b1100 !
b1100 /
18
01
04
17
b100 +
b100 $
b100 *
b100 '
#665
b1101 !
b1101 /
12
11
b101 +
b101 $
b101 *
b101 '
#670
02
b1110 !
b1110 /
15
01
14
b110 +
b110 $
b110 *
b110 '
#675
b1111 !
b1111 /
12
11
b111 +
b111 $
b111 *
b111 '
#680
02
05
08
b0 !
b0 /
0;
1"
01
04
07
1:
b1000 +
b1000 $
b1000 *
b1000 '
#685
b1 !
b1 /
12
11
b1001 +
b1001 $
b1001 *
b1001 '
#690
02
b10 !
b10 /
15
01
14
b1010 +
b1010 $
b1010 *
b1010 '
#695
b11 !
b11 /
12
11
b1011 +
b1011 $
b1011 *
b1011 '
#700
02
05
b100 !
b100 /
18
01
04
17
b1100 +
b1100 $
b1100 *
b1100 '
#705
b101 !
b101 /
12
11
b1101 +
b1101 $
b1101 *
b1101 '
#710
02
b110 !
b110 /
15
01
14
b1110 +
b1110 $
b1110 *
b1110 '
#715
b111 !
b111 /
12
11
b1111 +
b1111 $
b1111 *
b1111 '
#720
05
08
1;
0"
b1001 !
b1001 /
12
0.
01
04
07
0:
b0 +
10
b0 $
b0 *
b1001 #
b1001 )
b1001 &
b0 '
#725
15
b1010 !
b1010 /
02
1.
11
b1 +
b1 $
b1 *
b1 '
#730
08
0-
12
0.
b1011 !
b1011 /
15
01
14
b10 +
b10 $
b10 *
b10 '
#735
18
1-
05
b1100 !
b1100 /
02
1.
11
b11 +
b11 $
b11 *
b11 '
#740
0"
1;
0-
0,
12
0.
05
b1101 !
b1101 /
18
01
04
17
b100 +
b100 $
b100 *
b100 '
#745
15
b1110 !
b1110 /
02
1.
11
b101 +
b101 $
b101 *
b101 '
#750
0"
1;
0,
18
0-
12
0.
b1111 !
b1111 /
15
01
14
b110 +
b110 $
b110 *
b110 '
#755
1"
0;
1,
08
1-
05
b0 !
b0 /
02
1.
11
b111 +
b111 $
b111 *
b111 '
#760
0-
0,
12
0.
05
08
b1 !
b1 /
0;
01
04
07
1:
b1000 +
b1000 $
b1000 *
b1000 '
#765
15
b10 !
b10 /
02
1.
11
b1001 +
b1001 $
b1001 *
b1001 '
#770
08
0-
12
0.
b11 !
b11 /
15
01
14
b1010 +
b1010 $
b1010 *
b1010 '
#775
18
1-
05
b100 !
b100 /
02
1.
11
b1011 +
b1011 $
b1011 *
b1011 '
#780
0;
0-
0,
12
0.
05
b101 !
b101 /
18
01
04
17
b1100 +
b1100 $
b1100 *
b1100 '
#785
15
b110 !
b110 /
02
1.
11
b1101 +
b1101 $
b1101 *
b1101 '
#790
0;
0,
18
0-
12
0.
b111 !
b111 /
15
01
14
b1110 +
b1110 $
b1110 *
b1110 '
#795
1;
1,
08
1-
05
b1000 !
b1000 /
02
1.
11
b1111 +
b1111 $
b1111 *
b1111 '
#800
0"
0,
0-
08
1;
02
0.
b1010 !
b1010 /
15
01
04
07
0:
b0 +
00
13
b0 $
b0 *
b1010 #
b1010 )
b1010 &
b0 '
#805
b1011 !
b1011 /
12
11
b1 +
b1 $
b1 *
b1 '
#810
18
02
b1100 !
b1100 /
05
1-
01
14
b10 +
b10 $
b10 *
b10 '
#815
b1101 !
b1101 /
12
11
b11 +
b11 $
b11 *
b11 '
#820
0"
1;
0,
02
15
0-
b1110 !
b1110 /
18
01
04
17
b100 +
b100 $
b100 *
b100 '
#825
b1111 !
b1111 /
12
11
b101 +
b101 $
b101 *
b101 '
#830
1"
0;
1,
08
02
b0 !
b0 /
05
1-
01
14
b110 +
b110 $
b110 *
b110 '
#835
b1 !
b1 /
12
11
b111 +
b111 $
b111 *
b111 '
#840
0,
02
15
0-
08
b10 !
b10 /
0;
01
04
07
1:
b1000 +
b1000 $
b1000 *
b1000 '
#845
b11 !
b11 /
12
11
b1001 +
b1001 $
b1001 *
b1001 '
#850
18
02
b100 !
b100 /
05
1-
01
14
b1010 +
b1010 $
b1010 *
b1010 '
#855
b101 !
b101 /
12
11
b1011 +
b1011 $
b1011 *
b1011 '
#860
0;
0,
02
15
0-
b110 !
b110 /
18
01
04
17
b1100 +
b1100 $
b1100 *
b1100 '
#865
b111 !
b111 /
12
11
b1101 +
b1101 $
b1101 *
b1101 '
#870
1;
1,
08
02
b1000 !
b1000 /
05
1-
01
14
b1110 +
b1110 $
b1110 *
b1110 '
#875
b1001 !
b1001 /
12
11
b1111 +
b1111 $
b1111 *
b1111 '
#880
0"
0-
15
0,
08
1;
b1011 !
b1011 /
12
0.
01
04
07
0:
b0 +
10
b0 $
b0 *
b1011 #
b1011 )
b1011 &
b0 '
#885
18
1-
05
b1100 !
b1100 /
02
1.
11
b1 +
b1 $
b1 *
b1 '
#890
12
0.
b1101 !
b1101 /
05
01
14
b10 +
b10 $
b10 *
b10 '
#895
15
b1110 !
b1110 /
02
1.
11
b11 +
b11 $
b11 *
b11 '
#900
0"
0-
1;
0,
12
0.
15
b1111 !
b1111 /
18
01
04
17
b100 +
b100 $
b100 *
b100 '
#905
1"
0;
1,
08
1-
05
b0 !
b0 /
02
1.
11
b101 +
b101 $
b101 *
b101 '
#910
12
0.
b1 !
b1 /
05
01
14
b110 +
b110 $
b110 *
b110 '
#915
15
b10 !
b10 /
02
1.
11
b111 +
b111 $
b111 *
b111 '
#920
0-
0,
12
0.
15
08
b11 !
b11 /
0;
01
04
07
1:
b1000 +
b1000 $
b1000 *
b1000 '
#925
18
1-
05
b100 !
b100 /
02
1.
11
b1001 +
b1001 $
b1001 *
b1001 '
#930
12
0.
b101 !
b101 /
05
01
14
b1010 +
b1010 $
b1010 *
b1010 '
#935
15
b110 !
b110 /
02
1.
11
b1011 +
b1011 $
b1011 *
b1011 '
#940
0-
0;
0,
12
0.
15
b111 !
b111 /
18
01
04
17
b1100 +
b1100 $
b1100 *
b1100 '
#945
1;
1,
08
1-
05
b1000 !
b1000 /
02
1.
11
b1101 +
b1101 $
b1101 *
b1101 '
#950
12
0.
b1001 !
b1001 /
05
01
14
b1110 +
b1110 $
b1110 *
b1110 '
#955
15
b1010 !
b1010 /
02
1.
11
b1111 +
b1111 $
b1111 *
b1111 '
#960
0"
0,
0-
1;
02
0.
05
b1100 !
b1100 /
18
01
04
07
0:
b0 +
00
03
16
b0 $
b0 *
b1100 #
b1100 )
b1100 &
b0 '
#965
b1101 !
b1101 /
12
11
b1 +
b1 $
b1 *
b1 '
#970
02
b1110 !
b1110 /
15
01
14
b10 +
b10 $
b10 *
b10 '
#975
b1111 !
b1111 /
12
11
b11 +
b11 $
b11 *
b11 '
#980
1"
0;
02
05
b0 !
b0 /
08
1,
01
04
17
b100 +
b100 $
b100 *
b100 '
#985
b1 !
b1 /
12
11
b101 +
b101 $
b101 *
b101 '
#990
02
b10 !
b10 /
15
01
14
b110 +
b110 $
b110 *
b110 '
#995
b11 !
b11 /
12
11
b111 +
b111 $
b111 *
b111 '
#1000
02
05
18
0,
b100 !
b100 /
0;
01
04
07
1:
b1000 +
b1000 $
b1000 *
b1000 '
#1005
b101 !
b101 /
12
11
b1001 +
b1001 $
b1001 *
b1001 '
#1010
02
b110 !
b110 /
15
01
14
b1010 +
b1010 $
b1010 *
b1010 '
#1015
b111 !
b111 /
12
11
b1011 +
b1011 $
b1011 *
b1011 '
#1020
1;
02
05
b1000 !
b1000 /
08
1,
01
04
17
b1100 +
b1100 $
b1100 *
b1100 '
#1025
b1001 !
b1001 /
12
11
b1101 +
b1101 $
b1101 *
b1101 '
#1030
02
b1010 !
b1010 /
15
01
14
b1110 +
b1110 $
b1110 *
b1110 '
#1035
b1011 !
b1011 /
12
11
b1111 +
b1111 $
b1111 *
b1111 '
#1040
0"
05
18
0,
1;
b1101 !
b1101 /
12
0.
01
04
07
0:
b0 +
10
b0 $
b0 *
b1101 #
b1101 )
b1101 &
b0 '
#1045
15
b1110 !
b1110 /
02
1.
11
b1 +
b1 $
b1 *
b1 '
#1050
0"
1;
0,
18
0-
12
0.
b1111 !
b1111 /
15
01
14
b10 +
b10 $
b10 *
b10 '
#1055
1"
0;
1,
08
1-
05
b0 !
b0 /
02
1.
11
b11 +
b11 $
b11 *
b11 '
#1060
0-
12
0.
05
b1 !
b1 /
08
01
04
17
b100 +
b100 $
b100 *
b100 '
#1065
15
b10 !
b10 /
02
1.
11
b101 +
b101 $
b101 *
b101 '
#1070
08
0-
12
0.
b11 !
b11 /
15
01
14
b110 +
b110 $
b110 *
b110 '
#1075
18
1-
05
b100 !
b100 /
02
1.
11
b111 +
b111 $
b111 *
b111 '
#1080
0,
0-
12
0.
05
18
b101 !
b101 /
0;
01
04
07
1:
b1000 +
b1000 $
b1000 *
b1000 '
#1085
15
b110 !
b110 /
02
1.
11
b1001 +
b1001 $
b1001 *
b1001 '
#1090
0;
0,
18
0-
12
0.
b111 !
b111 /
15
01
14
b1010 +
b1010 $
b1010 *
b1010 '
#1095
1;
1,
08
1-
05
b1000 !
b1000 /
02
1.
11
b1011 +
b1011 $
b1011 *
b1011 '
#1100
0-
12
0.
05
b1001 !
b1001 /
08
01
04
17
b1100 +
b1100 $
b1100 *
b1100 '
#1105
15
b1010 !
b1010 /
02
1.
11
b1101 +
b1101 $
b1101 *
b1101 '
#1110
08
0-
12
0.
b1011 !
b1011 /
15
01
14
b1110 +
b1110 $
b1110 *
b1110 '
#1115
18
1-
05
b1100 !
b1100 /
02
1.
11
b1111 +
b1111 $
b1111 *
b1111 '
#1120
0"
0,
0-
18
1;
02
0.
b1110 !
b1110 /
15
01
04
07
0:
b0 +
00
13
b0 $
b0 *
b1110 #
b1110 )
b1110 &
b0 '
#1125
b1111 !
b1111 /
12
11
b1 +
b1 $
b1 *
b1 '
#1130
1"
0;
1,
08
02
b0 !
b0 /
05
1-
01
14
b10 +
b10 $
b10 *
b10 '
#1135
b1 !
b1 /
12
11
b11 +
b11 $
b11 *
b11 '
#1140
02
15
0-
b10 !
b10 /
08
01
04
17
b100 +
b100 $
b100 *
b100 '
#1145
b11 !
b11 /
12
11
b101 +
b101 $
b101 *
b101 '
#1150
18
02
b100 !
b100 /
05
1-
01
14
b110 +
b110 $
b110 *
b110 '
#1155
b101 !
b101 /
12
11
b111 +
b111 $
b111 *
b111 '
#1160
0,
02
15
0-
18
b110 !
b110 /
0;
01
04
07
1:
b1000 +
b1000 $
b1000 *
b1000 '
#1165
b111 !
b111 /
12
11
b1001 +
b1001 $
b1001 *
b1001 '
#1170
1;
1,
08
02
b1000 !
b1000 /
05
1-
01
14
b1010 +
b1010 $
b1010 *
b1010 '
#1175
b1001 !
b1001 /
12
11
b1011 +
b1011 $
b1011 *
b1011 '
#1180
02
15
0-
b1010 !
b1010 /
08
01
04
17
b1100 +
b1100 $
b1100 *
b1100 '
#1185
b1011 !
b1011 /
12
11
b1101 +
b1101 $
b1101 *
b1101 '
#1190
18
02
b1100 !
b1100 /
05
1-
01
14
b1110 +
b1110 $
b1110 *
b1110 '
#1195
b1101 !
b1101 /
12
11
b1111 +
b1111 $
b1111 *
b1111 '
#1200
0"
0,
0-
15
18
1;
b1111 !
b1111 /
12
0.
01
04
07
0:
b0 +
10
b0 $
b0 *
b1111 #
b1111 )
b1111 &
b0 '
#1205
1"
0;
1,
08
1-
05
b0 !
b0 /
02
1.
11
b1 +
b1 $
b1 *
b1 '
#1210
12
0.
b1 !
b1 /
05
01
14
b10 +
b10 $
b10 *
b10 '
#1215
15
b10 !
b10 /
02
1.
11
b11 +
b11 $
b11 *
b11 '
#1220
0-
12
0.
15
b11 !
b11 /
08
01
04
17
b100 +
b100 $
b100 *
b100 '
#1225
18
1-
05
b100 !
b100 /
02
1.
11
b101 +
b101 $
b101 *
b101 '
#1230
12
0.
b101 !
b101 /
05
01
14
b110 +
b110 $
b110 *
b110 '
#1235
15
b110 !
b110 /
02
1.
11
b111 +
b111 $
b111 *
b111 '
#1240
0,
0-
12
0.
15
18
b111 !
b111 /
0;
01
04
07
1:
b1000 +
b1000 $
b1000 *
b1000 '
#1245
1;
1,
08
1-
05
b1000 !
b1000 /
02
1.
11
b1001 +
b1001 $
b1001 *
b1001 '
#1250
12
0.
b1001 !
b1001 /
05
01
14
b1010 +
b1010 $
b1010 *
b1010 '
#1255
15
b1010 !
b1010 /
02
1.
11
b1011 +
b1011 $
b1011 *
b1011 '
#1260
0-
12
0.
15
b1011 !
b1011 /
08
01
04
17
b1100 +
b1100 $
b1100 *
b1100 '
#1265
18
1-
05
b1100 !
b1100 /
02
1.
11
b1101 +
b1101 $
b1101 *
b1101 '
#1270
12
0.
b1101 !
b1101 /
05
01
14
b1110 +
b1110 $
b1110 *
b1110 '
#1275
15
b1110 !
b1110 /
02
1.
11
b1111 +
b1111 $
b1111 *
b1111 '
#1280
05
08
0;
00
03
06
09
b0 !
b0 /
02
b0 $
b0 *
b0 #
b0 )
1%
b1 (
b0 &
b0 '
#1285
0"
1;
0,
18
0-
15
0.
b1111 !
b1111 /
12
01
b1110 +
b1 $
b1 *
b1 '
#1290
1.
02
b1110 !
b1110 /
15
11
04
b1101 +
b10 $
b10 *
b10 '
#1295
05
0.
b1101 !
b1101 /
12
01
b1100 +
b11 $
b11 *
b11 '
#1300
1-
1.
02
05
b1100 !
b1100 /
18
11
14
07
b1011 +
b100 $
b100 *
b100 '
#1305
08
0-
15
0.
b1011 !
b1011 /
12
01
b1010 +
b101 $
b101 *
b101 '
#1310
1.
02
b1010 !
b1010 /
15
11
04
b1001 +
b110 $
b110 *
b110 '
#1315
05
0.
b1001 !
b1001 /
12
01
b1000 +
b111 $
b111 *
b111 '
#1320
1,
1-
1.
02
05
08
b1000 !
b1000 /
1;
11
14
17
0:
b111 +
b1000 $
b1000 *
b1000 '
